{
  "AllFeedbacks": [
    {
      "brand": "Audi",
      "feedback": "This is a feedback"
    },
    {
      "brand": "BMW",
      "feedback": "This is a feedback"
    },
    {
      "brand": "Mercedes",
      "feedback": "This is a feedback"
    },
    {
      "brand": "Lamborghini",
      "feedback": "This is a feedback"
    },
    {
      "brand": "Ferrari",
      "feedback": "This is a feedback"
    },
    {
      "brand": "Porsche",
      "feedback": "This is a feedback"
    },
    {
      "brand": "Jaguar",
      "feedback": "This is a feedback"
    }
  ]
}
